tfts/__init__.py
tfts/constants.py
tfts/data/__init__.py
tfts/data/get_data.py
tfts/data/timeseries.py
tfts/features/__init__.py
tfts/features/datetime_feature.py
tfts/features/norm.py
tfts/features/one_order_feature.py
tfts/features/registry.py
tfts/features/two_order_feature.py
tfts/generator.py
tfts/layers/__init__.py
tfts/layers/attention_layer.py
tfts/layers/autoformer_layer.py
tfts/layers/cnn_layer.py
tfts/layers/dense_layer.py
tfts/layers/embed_layer.py
tfts/layers/mask_layer.py
tfts/layers/moe_layer.py
tfts/layers/nbeats_layer.py
tfts/layers/position_layer.py
tfts/layers/rwkv_layer.py
tfts/layers/unet_layer.py
tfts/layers/util_layer.py
tfts/models/__init__.py
tfts/models/auto_config.py
tfts/models/auto_model.py
tfts/models/autoformer.py
tfts/models/base.py
tfts/models/bert.py
tfts/models/deep_ar.py
tfts/models/diffusion.py
tfts/models/dlinear.py
tfts/models/gpt.py
tfts/models/informer.py
tfts/models/nbeats.py
tfts/models/patches_tst.py
tfts/models/pfn.py
tfts/models/rnn.py
tfts/models/rwkv.py
tfts/models/seq2seq.py
tfts/models/tcn.py
tfts/models/tft.py
tfts/models/tide.py
tfts/models/timesfm.py
tfts/models/transformer.py
tfts/models/unet.py
tfts/models/wavenet.py
tfts/pipelines/__init__.py
tfts/pipelines/base.py
tfts/tasks/__init__.py
tfts/tasks/auto_task.py
tfts/tasks/base.py
tfts/trainer.py
tfts/training_args.py
tfts-0.0.19.dist-info/LICENSE
tfts-0.0.19.dist-info/METADATA
tfts-0.0.19.dist-info/WHEEL
tfts-0.0.19.dist-info/RECORD
