Metadata-Version: 2.3
Name: tfts
Version: 0.0.19
Summary: Deep learning time series with TensorFlow
Author: Longxing Tan
Requires-Python: >=3.8,<=3.13
Classifier: Intended Audience :: Developers
Classifier: Intended Audience :: Science/Research
Classifier: License :: OSI Approved :: MIT License
Classifier: Programming Language :: Python :: 3
Classifier: Programming Language :: Python :: 3.8
Classifier: Programming Language :: Python :: 3.9
Classifier: Programming Language :: Python :: 3.10
Classifier: Programming Language :: Python :: 3.11
Classifier: Programming Language :: Python :: 3.12
Classifier: Programming Language :: Python :: 3.13
Classifier: Topic :: Scientific/Engineering
Classifier: Topic :: Scientific/Engineering :: Artificial Intelligence
Classifier: Topic :: Scientific/Engineering :: Mathematics
Classifier: Topic :: Software Development
Classifier: Topic :: Software Development :: Libraries
Classifier: Topic :: Software Development :: Libraries :: Python Modules
Requires-Dist: pandas (>=1.3.0)
Project-URL: Documentation, https://time-series-prediction.readthedocs.io
Project-URL: Homepage, https://time-series-prediction.readthedocs.io
Project-URL: Repository, https://github.com/LongxingTan/Time-series-prediction
